biddmanager_pkg/__init__.py
biddmanager_pkg/biddmanager.py
biddmanager_pkg-0.1.0.dist-info/LICENSE
biddmanager_pkg-0.1.0.dist-info/METADATA
biddmanager_pkg-0.1.0.dist-info/WHEEL
biddmanager_pkg-0.1.0.dist-info/top_level.txt
biddmanager_pkg-0.1.0.dist-info/RECORD
