Metadata-Version: 2.1
Name: biddmanager_pkg
Version: 0.1.0
Summary: this libarbary is for managing the bids of user 
Home-page: https://github.com/your_username/your_repository
Author: rahul shirsat
Author-email: rahulshirsat9156@gmail.com
Classifier: Programming Language :: Python :: 3
Classifier: License :: OSI Approved :: MIT License
Classifier: Operating System :: OS Independent
Requires-Python: >=3.6
License-File: LICENSE
